MANIFEST.in
setup.cfg
setup.py
tw/__init__.py
tw.rating.egg-info/PKG-INFO
tw.rating.egg-info/SOURCES.txt
tw.rating.egg-info/dependency_links.txt
tw.rating.egg-info/entry_points.txt
tw.rating.egg-info/namespace_packages.txt
tw.rating.egg-info/not-zip-safe
tw.rating.egg-info/requires.txt
tw.rating.egg-info/top_level.txt
tw/rating/__init__.py
tw/rating/release.py
tw/rating/widgets.py
tw/rating/static/_star.gif
tw/rating/static/delete.gif
tw/rating/static/delete.png
tw/rating/static/jquery.rating.js
tw/rating/static/ratings.css
tw/rating/static/star.gif
tw/rating/static/star.png
tw/rating/static/star_off.gif
tw/rating/static/star_on.gif