Metadata-Version: 1.0
Name: tw.rating
Version: 0.8
Summary: Star Rater plugin
Home-page: http://toscawidgets.org/
Author: Christopher Perkins, Alberto Valverde, Sean O'Donnell
Author-email: chris@percious.com
License: UNKNOWN
Download-URL: http://toscawidgets.org/download
Keywords: toscawidgets.widgets
Platform: UNKNOWN
